setup.py
leon_distributions/Binomialdistribution.py
leon_distributions/Gaussiandistribution.py
leon_distributions/Generaldistribution.py
leon_distributions/__init__.py
leon_distributions.egg-info/PKG-INFO
leon_distributions.egg-info/SOURCES.txt
leon_distributions.egg-info/dependency_links.txt
leon_distributions.egg-info/not-zip-safe
leon_distributions.egg-info/top_level.txt