Metadata-Version: 1.0
Name: leon-distributions
Version: 1.0
Summary: Gaussian and Binomial distributions
Home-page: UNKNOWN
Author: Panayiotis Leontiou
Author-email: UNKNOWN
License: UNKNOWN
Platform: UNKNOWN
